lona_chartjs/__init__.py
lona_chartjs/html.py
lona_chartjs/static/lona-chartjs/chartjs-widgets.js
lona_chartjs/static/lona-chartjs/dist/chart.esm.js
lona_chartjs/static/lona-chartjs/dist/chart.js
lona_chartjs/static/lona-chartjs/dist/chart.min.js
lona_chartjs/static/lona-chartjs/dist/helpers.esm.js
lona_chartjs/static/lona-chartjs/dist/chunks/helpers.segment.js
lona_chartjs-0.2.1.dist-info/LICENSE.txt
lona_chartjs-0.2.1.dist-info/METADATA
lona_chartjs-0.2.1.dist-info/WHEEL
lona_chartjs-0.2.1.dist-info/top_level.txt
lona_chartjs-0.2.1.dist-info/RECORD
