Metadata-Version: 2.1
Name: lona-chartjs
Version: 0.2.1
Summary: Chart.js bindings for Lona
Author-email: Florian Scherf <mail@florianscherf.de>
License: MIT License
Project-URL: Homepage, https://github.com/lona-web-org/lona-chartjs
Project-URL: Repository, https://github.com/lona-web-org/lona-chartjs
Project-URL: Bug Tracker, https://github.com/lona-web-org/lona-chartjs/issues
Classifier: License :: OSI Approved :: MIT License
Requires-Python: >=3.7
License-File: LICENSE.txt
Requires-Dist: lona (>=1.10.5)
Provides-Extra: packaging
Requires-Dist: build ; extra == 'packaging'
Requires-Dist: twine ; extra == 'packaging'
